setup.py
MarkovMixing.egg-info/PKG-INFO
MarkovMixing.egg-info/SOURCES.txt
MarkovMixing.egg-info/dependency_links.txt
MarkovMixing.egg-info/requires.txt
MarkovMixing.egg-info/top_level.txt
markovmixing/__init__.py
markovmixing/distributions.py
markovmixing/iterate_distributions.py
markovmixing/networkx_graphs.py
markovmixing/plot_util.py
markovmixing/transition_matrix.py
markovmixing/video_util.py
markovmixing/classes/__init__.py
markovmixing/classes/markovchain.py
markovmixing/tests/__init__.py
markovmixing/tests/test_distributions.py
markovmixing/tests/test_iteration.py
markovmixing/tests/test_markovchain.py
markovmixing/tests/test_networkx_graphs.py
markovmixing/tests/test_transition_matrix.py