Metadata-Version: 1.0
Name: MarkovMixing
Version: 0.0.2
Summary: Determine mixing times for Markov chains with ~ 100.000 states.
Home-page: https://github.com/sbordt/markovmixing
Author: S. Bordt
Author-email: sbordt@posteo.de
License: MIT
Platform: UNKNOWN
